{
  "info": {
    "name": "Recruitment System API",
    "description": "API collection for Recruitment System - Spring Boot Application",
    "schema": "https://schema.getpostman.com/json/collection/v2.1.0/collection.json"
  },
  "auth": {
    "type": "bearer",
    "bearer": [
      {
        "key": "token",
        "value": "{{token}}",
        "type": "string"
      }
    ]
  },
  "variable": [
    {
      "key": "base_url",
      "value": "http://localhost:8081"
    },
    {
      "key": "token",
      "value": ""
    }
  ],
  "item": [
    {
      "name": "Authentication",
      "item": [
        {
          "name": "Register New User",
          "request": {
            "method": "POST",
            "header": [
              {
                "key": "Content-Type",
                "value": "application/json"
              }
            ],
            "body": {
              "mode": "raw",
              "raw": "{\n  \"email\": \"john.doe@example.com\",\n  \"password\": \"password123\",\n  \"firstName\": \"John\",\n  \"lastName\": \"Doe\",\n  \"role\": \"APPLICANT\"\n}"
            },
            "url": {
              "raw": "{{base_url}}/api/auth/register",
              "host": ["{{base_url}}"],
              "path": ["api", "auth", "register"]
            }
          },
          "response": []
        },
        {
          "name": "Login User",
          "request": {
            "method": "POST",
            "header": [
              {
                "key": "Content-Type",
                "value": "application/json"
              }
            ],
            "body": {
              "mode": "raw",
              "raw": "{\n  \"email\": \"john.doe@example.com\",\n  \"password\": \"password123\"\n}"
            },
            "url": {
              "raw": "{{base_url}}/api/auth/login",
              "host": ["{{base_url}}"],
              "path": ["api", "auth", "login"]
            }
          },
          "response": []
        },
        {
          "name": "Register Employer",
          "request": {
            "method": "POST",
            "header": [
              {
                "key": "Content-Type",
                "value": "application/json"
              }
            ],
            "body": {
              "mode": "raw",
              "raw": "{\n  \"email\": \"employer@company.com\",\n  \"password\": \"employer123\",\n  \"firstName\": \"Manager\",\n  \"lastName\": \"Smith\",\n  \"role\": \"EMPLOYER\",\n  \"companyName\": \"Tech Company Inc\"\n}"
            },
            "url": {
              "raw": "{{base_url}}/api/auth/register",
              "host": ["{{base_url}}"],
              "path": ["api", "auth", "register"]
            }
          },
          "response": []
        },
        {
          "name": "Register Admin",
          "request": {
            "method": "POST",
            "header": [
              {
                "key": "Content-Type",
                "value": "application/json"
              }
            ],
            "body": {
              "mode": "raw",
              "raw": "{\n  \"email\": \"admin@system.com\",\n  \"password\": \"admin123\",\n  \"firstName\": \"System\",\n  \"lastName\": \"Admin\",\n  \"role\": \"ADMIN\"\n}"
            },
            "url": {
              "raw": "{{base_url}}/api/auth/register",
              "host": ["{{base_url}}"],
              "path": ["api", "auth", "register"]
            }
          },
          "response": []
        }
      ]
    },
    {
      "name": "User Profile",
      "item": [
        {
          "name": "Get Current User Profile",
          "request": {
            "method": "GET",
            "header": [],
            "url": {
              "raw": "{{base_url}}/api/user/profile",
              "host": ["{{base_url}}"],
              "path": ["api", "user", "profile"]
            }
          },
          "response": []
        },
        {
          "name": "Update User Profile",
          "request": {
            "method": "PUT",
            "header": [
              {
                "key": "Content-Type",
                "value": "application/json"
              }
            ],
            "body": {
              "mode": "raw",
              "raw": "{\n  \"firstName\": \"Updated First\",\n  \"lastName\": \"Updated Last\",\n  \"phoneNumber\": \"+84123456789\"\n}"
            },
            "url": {
              "raw": "{{base_url}}/api/user/profile",
              "host": ["{{base_url}}"],
              "path": ["api", "user", "profile"]
            }
          },
          "response": []
        }
      ]
    },
    {
      "name": "Public Endpoints",
      "item": [
        {
          "name": "Search Jobs (Public)",
          "request": {
            "method": "GET",
            "header": [],
            "url": {
              "raw": "{{base_url}}/api/jobs/search?keyword=developer&location=hanoi",
              "host": ["{{base_url}}"],
              "path": ["api", "jobs", "search"],
              "query": [
                {
                  "key": "keyword",
                  "value": "developer"
                },
                {
                  "key": "location",
                  "value": "hanoi"
                }
              ]
            }
          },
          "response": []
        },
        {
          "name": "Get Public Companies",
          "request": {
            "method": "GET",
            "header": [],
            "url": {
              "raw": "{{base_url}}/api/companies/public",
              "host": ["{{base_url}}"],
              "path": ["api", "companies", "public"]
            }
          },
          "response": []
        }
      ]
    },
    {
      "name": "Applicant Endpoints",
      "item": [
        {
          "name": "Get My Applications",
          "request": {
            "method": "GET",
            "header": [],
            "url": {
              "raw": "{{base_url}}/api/applications/my",
              "host": ["{{base_url}}"],
              "path": ["api", "applications", "my"]
            }
          },
          "response": []
        },
        {
          "name": "Apply for Job",
          "request": {
            "method": "POST",
            "header": [
              {
                "key": "Content-Type",
                "value": "application/json"
              }
            ],
            "body": {
              "mode": "raw",
              "raw": "{\n  \"jobId\": 1,\n  \"coverLetter\": \"I am very interested in this position...\"\n}"
            },
            "url": {
              "raw": "{{base_url}}/api/applications/apply",
              "host": ["{{base_url}}"],
              "path": ["api", "applications", "apply"]
            }
          },
          "response": []
        },
        {
          "name": "Get My Profile Details",
          "request": {
            "method": "GET",
            "header": [],
            "url": {
              "raw": "{{base_url}}/api/profiles/my",
              "host": ["{{base_url}}"],
              "path": ["api", "profiles", "my"]
            }
          },
          "response": []
        }
      ]
    },
    {
      "name": "Employer Endpoints",
      "item": [
        {
          "name": "Create Job Posting",
          "request": {
            "method": "POST",
            "header": [
              {
                "key": "Content-Type",
                "value": "application/json"
              }
            ],
            "body": {
              "mode": "raw",
              "raw": "{\n  \"title\": \"Senior Java Developer\",\n  \"description\": \"We are looking for a senior Java developer...\",\n  \"requirements\": \"3+ years experience with Spring Boot, MySQL\",\n  \"benefits\": \"Competitive salary, health insurance\",\n  \"salaryMin\": 1500,\n  \"salaryMax\": 2500,\n  \"location\": \"Ho Chi Minh City\",\n  \"jobType\": \"FULL_TIME\",\n  \"experienceLevel\": \"SENIOR\",\n  \"applicationDeadline\": \"2025-12-31T23:59:59\"\n}"
            },
            "url": {
              "raw": "{{base_url}}/api/employer/jobs",
              "host": ["{{base_url}}"],
              "path": ["api", "employer", "jobs"]
            }
          },
          "response": []
        },
        {
          "name": "Get My Job Postings",
          "request": {
            "method": "GET",
            "header": [],
            "url": {
              "raw": "{{base_url}}/api/employer/jobs",
              "host": ["{{base_url}}"],
              "path": ["api", "employer", "jobs"]
            }
          },
          "response": []
        },
        {
          "name": "Get Applications for My Jobs",
          "request": {
            "method": "GET",
            "header": [],
            "url": {
              "raw": "{{base_url}}/api/employer/applications",
              "host": ["{{base_url}}"],
              "path": ["api", "employer", "applications"]
            }
          },
          "response": []
        }
      ]
    },
    {
      "name": "Admin Endpoints",
      "item": [
        {
          "name": "Get All Users",
          "request": {
            "method": "GET",
            "header": [],
            "url": {
              "raw": "{{base_url}}/api/admin/users",
              "host": ["{{base_url}}"],
              "path": ["api", "admin", "users"]
            }
          },
          "response": []
        },
        {
          "name": "Get System Reports",
          "request": {
            "method": "GET",
            "header": [],
            "url": {
              "raw": "{{base_url}}/api/admin/reports",
              "host": ["{{base_url}}"],
              "path": ["api", "admin", "reports"]
            }
          },
          "response": []
        },
        {
          "name": "Update User Status",
          "request": {
            "method": "PUT",
            "header": [
              {
                "key": "Content-Type",
                "value": "application/json"
              }
            ],
            "body": {
              "mode": "raw",
              "raw": "{\n  \"status\": \"ACTIVE\"\n}"
            },
            "url": {
              "raw": "{{base_url}}/api/admin/users/4/status",
              "host": ["{{base_url}}"],
              "path": ["api", "admin", "users", "4", "status"]
            }
          },
          "response": []
        }
      ]
    },
    {
      "name": "Error Test Cases",
      "item": [
        {
          "name": "Invalid Email Format",
          "request": {
            "method": "POST",
            "header": [
              {
                "key": "Content-Type",
                "value": "application/json"
              }
            ],
            "body": {
              "mode": "raw",
              "raw": "{\n  \"email\": \"invalid-email\",\n  \"password\": \"123456\"\n}"
            },
            "url": {
              "raw": "{{base_url}}/api/auth/login",
              "host": ["{{base_url}}"],
              "path": ["api", "auth", "login"]
            }
          },
          "response": []
        },
        {
          "name": "Unauthorized Access",
          "request": {
            "method": "GET",
            "header": [],
            "url": {
              "raw": "{{base_url}}/api/user/profile",
              "host": ["{{base_url}}"],
              "path": ["api", "user", "profile"]
            },
            "auth": {
              "type": "noauth"
            }
          },
          "response": []
        },
        {
          "name": "Wrong Credentials",
          "request": {
            "method": "POST",
            "header": [
              {
                "key": "Content-Type",
                "value": "application/json"
              }
            ],
            "body": {
              "mode": "raw",
              "raw": "{\n  \"email\": \"nonexistent@example.com\",\n  \"password\": \"wrongpassword\"\n}"
            },
            "url": {
              "raw": "{{base_url}}/api/auth/login",
              "host": ["{{base_url}}"],
              "path": ["api", "auth", "login"]
            }
          },
          "response": []
        }
      ]
    }
  ]
}